
{
  "appTitle": "RealPrice Finder",
  "appDescription": "Find the best local prices for products and services.",
  "navbar": {
    "offers": "Offers",
    "analyzeImage": "Analyze Image",
    "forStores": "For Stores",
    "appName": "RealPrice Finder",
    "monitoring": "Monitoring"
  },
  "bottomNavbar": {
    "offers": "Offers",
    "analyze": "Analyze",
    "stores": "Stores",
    "monitoring": "Monitor"
  },
  "homePage": {
    "searchPlaceholder": "Search for products, stores, or categories...",
    "sortBy": "Sort by:",
    "proximity": "Proximity",
    "price": "Price",
    "allCategories": "All",
    "noOffersFound": "No Offers Found",
    "noOffersFoundForSearch": "No offers found for \"{searchTerm}\". Try different keywords or clear the search.",
    "noOffersAdvice": "Try adjusting your search or filters. No active advertisements available.",
    "loadingOffersText": "Loading offers...",
    "errorLoadingOffersTitle": "Error Loading Offers",
    "errorLoadingOffersMessage": "Could not fetch offers at this time. Please try again later.",
    "getLocationButton": "Use My Location",
    "updateLocationButton": "Update Location",
    "locationErrorTitle": "Location Error",
    "locationPermissionDenied": "Location permission was denied. Please enable it in your browser settings to sort by proximity.",
    "locationUnavailable": "Your location is currently unavailable. Please try again or check your device settings.",
    "locationTimeout": "Could not get your location in time. Please try again.",
    "locationUnknownError": "An unknown error occurred while trying to get your location.",
    "distanceAway": "away",
    "distanceUnknown": "Distance unknown",
    "viewDealButton": "View Deal",
    "confirmLocationAccessTitle": "Use Your Location?",
    "confirmLocationAccessMessage": "To sort offers by proximity and show distances, we need your permission to access your current location. Your location data is used only for this purpose.",
    "allowLocationButton": "Allow",
    "cancelLocationButton": "Cancel"
  },
  "productCategoryNames": {
    "electronics": "Electronics",
    "clothing": "Clothing",
    "home-kitchen": "Home & Kitchen",
    "books": "Books",
    "groceries": "Groceries",
    "other": "Other"
  },
  "localeSwitcher": {
    "label": "Change language:",
    "pt": "Portuguese",
    "en": "English",
    "es": "Spanish"
  },
  "imageAnalysisTool": {
    "title": "Analyze Image for Product ID",
    "description": "Upload an image or use your camera to identify a product.",
    "uploadLabel": "Upload Image or Use Camera",
    "uploadButton": "Upload a file",
    "dragAndDrop": "or drag and drop",
    "fileTypes": "PNG, JPG, GIF, WebP up to 10MB",
    "selectedImageAlt": "Selected image for analysis",
    "clearImage": "Clear image/camera",
    "openCameraButton": "Open Camera",
    "closeCameraButton": "Close Camera",
    "takePhotoButton": "Take Photo",
    "cameraNotSupported": "Camera API is not supported by your browser or device.",
    "cameraAccessDeniedMessage": "Camera access was denied. Please enable it in your browser settings.",
    "cameraErrorTitle": "Camera Error",
    "cameraPermissionWasDenied": "Camera permission was denied. Please enable it in your browser settings to use this feature.",
    "errorTitle": "Error",
    "errorSelectImage": "Please select an image file (JPEG, PNG, GIF, WebP).",
    "errorSelectImageFirst": "Please select or capture an image first.",
    "errorFailedAnalysis": "Failed to analyze image. Please try again.",
    "analyzeButton": "Identify Product",
    "analyzingButton": "Identifying...",
    "analysisCompleteToastTitle": "Analysis Complete",
    "analysisCompleteToastDesc": "Identified: {productIdentification}",
    "analysisFailedToastTitle": "Analysis Failed",
    "analysisFailedToastDesc": "An error occurred during image analysis.",
    "productIdentifiedTitle": "Product Identified",
    "searchOffersFor": "Search offers for \"{productIdentification}\""
  },
  "auth": {
    "signInLink": "Sign In",
    "signUpLink": "Sign Up",
    "signOutLink": "Sign Out",
    "signOutLinkShort": "Sign Out",
    "myAccountLink": "My Account",
    "myStoreLink": "My Store",
    "myProductsLink": "My Products",
    "myProductsLinkShort": "Products",
    "signOutSuccessTitle": "Signed Out Successfully!",
    "signOutSuccessMessage": "You have been signed out.",
    "signOutErrorTitle": "Sign Out Error",
    "mustBeLoggedInStoreRegistrationTitle": "Access Restricted",
    "mustBeLoggedInStoreRegistrationMessage": "You must be logged in as a store owner to register a new store. Please sign in or sign up.",
    "mustBeLoggedInProductListingTitle": "Access Restricted",
    "mustBeLoggedInProductListingMessage": "You must be logged in as a store owner to list products. Please sign in or sign up."
  },
  "authForms": {
    "emailLabel": "Email",
    "emailPlaceholder": "your@email.com",
    "passwordLabel": "Password",
    "confirmPasswordLabel": "Confirm Password",
    "signInTitle": "Sign In to Your Store Account",
    "signInDescription": "Access your account to manage your store and products.",
    "signInButton": "Sign In",
    "signingInButton": "Signing In...",
    "signUpTitle": "Create Your Store Account",
    "signUpDescription": "Sign up to start listing your products.",
    "signUpButton": "Sign Up",
    "signingUpButton": "Signing Up...",
    "dontHaveAccount": "Don't have an account?",
    "alreadyHaveAccount": "Already have an account?",
    "signInLink": "Sign In",
    "signUpLink": "Sign Up",
    "emailInvalidError": "Please enter a valid email address.",
    "passwordMinLengthError": "Password must be at least {length} characters.",
    "passwordRequiredError": "Password is required.",
    "passwordsDontMatchError": "Passwords do not match.",
    "signUpSuccessTitle": "Sign Up Successful!",
    "signUpSuccessMessage": "Your account has been created. You can now register your store.",
    "signUpErrorTitle": "Sign Up Error",
    "signInSuccessTitle": "Sign In Successful!",
    "signInSuccessMessage": "Welcome back!",
    "signInErrorTitle": "Sign In Error",
    "firebaseErrors": {
      "auth/email-already-in-use": "This email is already in use. Try signing in or use a different email.",
      "auth/invalid-email": "The email format is invalid.",
      "auth/operation-not-allowed": "Operation not allowed. Contact support.",
      "auth/weak-password": "The password is too weak. Try a stronger one.",
      "auth/user-disabled": "This user account has been disabled.",
      "auth/user-not-found": "No user found with this email. Check the email or sign up.",
      "auth/wrong-password": "Incorrect password. Check your password and try again.",
      "auth/invalid-credential": "Invalid credentials. Check your email and password."
    },
    "formLoadingText": "Form loading..."
  },
  "storeRegistrationForm": {
    "formTitle": "Register Your Store",
    "formDescription": "Join RealPrice Finder to list your products and reach more customers.",
    "storeNameLabel": "Store Name",
    "storeNamePlaceholder": "e.g., The Corner Cafe",
    "storeNameMinLengthError": "Store name must be at least {length} characters.",
    "emailLabel": "Contact Email",
    "emailPlaceholder": "you@example.com",
    "emailInvalidError": "Please enter a valid email.",
    "phoneLabel": "Contact Phone",
    "phonePlaceholder": "(555) 123-4567",
    "phoneMinLengthError": "Phone number must be at least {length} digits.",
    "addressLabel": "Street Address",
    "addressPlaceholder": "123 Main St",
    "addressMinLengthError": "Address must be at least {length} characters.",
    "cityLabel": "City",
    "cityPlaceholder": "Anytown",
    "cityMinLengthError": "City must be at least {length} characters.",
    "stateLabel": "State",
    "statePlaceholder": "CA",
    "stateMinLengthError": "State must be at least {length} characters.",
    "zipCodeLabel": "Zip Code",
    "zipCodePlaceholder": "90210",
    "zipCodeMinLengthError": "Zip code must be at least {length} digits.",
    "latitudeLabel": "Latitude",
    "latitudePlaceholder": "e.g., 34.0522",
    "longitudeLabel": "Longitude",
    "longitudePlaceholder": "e.g., -118.2437",
    "latitudeInvalidError": "Latitude must be between -90 and 90.",
    "longitudeInvalidError": "Longitude must be between -180 and 180.",
    "coordinatesHint": "Optional. Helps users find your store. You can use Google Maps to find the latitude and longitude of your address.",
    "categoryLabel": "Store Category",
    "categoryPlaceholder": "Select a category for your store",
    "categoryRequiredError": "Please select a store category.",
     "categoryOptions": {
        "Restaurant": "Restaurant",
        "Retail": "Retail",
        "Services": "Services",
        "Other": "Other"
    },
    "descriptionLabel": "Store Description (Optional)",
    "descriptionPlaceholder": "Tell us a bit about your store...",
    "descriptionHint": "A brief description of your store and what you offer.",
    "submitButton": "Register Store",
    "submittingButton": "Registering...",
    "registrationSuccessTitle": "Registration Submitted!",
    "registrationSuccessMessage": "Thank you, {storeName}, for registering. Your store data has been saved.",
    "registrationErrorTitle": "Registration Failed",
    "genericError": "An error occurred. Please try again.",
    "formLoadingText": "Form loading..."
  },
  "productListingPage": {
    "loadingProductPageText": "Loading...",
    "errorFetchingStoreTitle": "Error Fetching Store",
    "errorFetchingStoreMessage": "Could not load your store data. Please try again. Error: ",
    "noStoreFoundTitle": "No Store Found",
    "noStoreFoundMessage": "It looks like you haven't registered a store yet. Please register your store to list products.",
    "registerStoreButton": "Register My Store"
  },
  "productListingForm": {
    "formTitle": "Advertise New Product",
    "formDescription": "Add products to your store's (ID: {storeId}) advertisements on RealPrice Finder.",
    "productNameLabel": "Product Name",
    "productNamePlaceholder": "e.g., Handcrafted Leather Wallet",
    "productNameMinLengthError": "Product name must be at least {length} characters.",
    "descriptionLabel": "Product Description (Optional)",
    "descriptionPlaceholder": "Describe your product in detail...",
    "descriptionMinLengthError": "Description must be at least {length} characters.",
    "priceLabel": "Price",
    "pricePositiveError": "Price must be a positive number.",
    "categoryLabel": "Product Category",
    "categoryPlaceholder": "Select product category",
    "categoryRequiredError": "Please select a product category.",
    "imageUrlLabel": "Product Image URL (Optional)",
    "imageUrlHint": "Link to an image of your product. Use https://placehold.co for placeholders.",
    "imageUrlInvalidError": "Please enter a valid image URL.",
    "dataAiHintLabel": "Image AI Hint (Optional)",
    "dataAiHintPlaceholder": "e.g. red shirt, headphones",
    "dataAiHintDescription": "Keywords (1-2) if URL is a placeholder, to help find real images. Max {length} chars.",
    "dataAiHintMaxLengthError": "AI hint must be at most {length} characters.",
    "stockLabel": "Stock Quantity (Optional)",
    "stockPlaceholder": "Leave blank if not tracking",
    "stockHint": "Number of items currently in stock.",
    "stockNonNegativeError": "Stock quantity cannot be negative.",
    "validityLabel": "Advertisement Validity",
    "validityPlaceholder": "Select validity period",
    "validityHint": "How long this ad will be active ({minDays}-{maxDays} days).",
    "validityMinDaysError": "Validity must be at least {days} day.",
    "validityMaxDaysError": "Validity must be at most {days} days.",
    "day": "day",
    "days": "days",
    "submitButton": "Advertise Product",
    "submittingButton": "Advertising...",
    "productAdvertisedTitle": "Product Advertised!",
    "productAdvertisedMessage": "{productName} has been successfully advertised.",
    "advertisingFailedTitle": "Advertising Failed",
    "advertisingFailedMessage": "There was an error posting your advertisement. Please try again.",
    "formLoadingText": "Form loading..."
  },
  "monitoringPage": {
    "title": "Price Monitoring",
    "description": "View aggregated price data and trends from product advertisement history.",
    "loadingText": "Loading monitoring data...",
    "errorLoadingTitle": "Error Loading Monitoring Data",
    "errorLoadingMessage": "Could not fetch price history data. Please try again later.",
    "noHistoryFound": "No Price History Data",
    "noHistoryFoundMessage": "There is no price history data available to display yet. Expired advertisements will appear here.",
    "selectProductPlaceholder": "Select a product to view history",
    "tableTitle": "Price History for: {productName}",
    "productColumn": "Product",
    "priceColumn": "Price",
    "storeColumn": "Store",
    "dateColumn": "Date Archived",
    "priceTrendChartTitle": "Price Trend for {productName}",
    "noDataForProduct": "No price history data available for the selected product."
  }
}
